ontor/__init__.py
ontor/_about.py
ontor/ontor.py
ontor/config/__init__.py
ontor/config/network_visualization.config
ontor/queries/__init__.py
ontor/queries/class_axioms.sparql
ontor/queries/dp_axioms.sparql
ontor/queries/op_axioms.sparql
ontor/queries/prefixes.sparql
ontor-0.4.11.dist-info/LICENSE
ontor-0.4.11.dist-info/METADATA
ontor-0.4.11.dist-info/WHEEL
ontor-0.4.11.dist-info/top_level.txt
ontor-0.4.11.dist-info/RECORD
