Metadata-Version: 2.1
Name: ontor
Version: 0.4.11
Summary: ontor - an ontology editor based on Owlready2
Home-page: https://github.com/felixocker/ontor
Download-URL: https://github.com/felixocker/ontor/archive/refs/tags/v0.4.11.tar.gz
Author: Felix Ocker
Author-email: felix.ocker@googlemail.com
Project-URL: Bug Tracker, https://github.com/felixocker/ontor/issues
Keywords: ontology,owl,python,knowledge graph
Classifier: Programming Language :: Python :: 3
Classifier: License :: OSI Approved :: GNU General Public License v3 or later (GPLv3+)
Classifier: Operating System :: OS Independent
Requires-Python: >=3.9
License-File: LICENSE
Requires-Dist: networkx
Requires-Dist: owlready2
Requires-Dist: pandas
Requires-Dist: pyvis (==0.1.9)
